AUTHORS.txt
CHANGES.txt
LICENSE.txt
MANIFEST.in
README.md
TEST.txt
VERSION.txt
setup.py
EbookLib.egg-info/PKG-INFO
EbookLib.egg-info/SOURCES.txt
EbookLib.egg-info/dependency_links.txt
EbookLib.egg-info/requires.txt
EbookLib.egg-info/top_level.txt
docs/Makefile
docs/conf.py
docs/ebooklib.plugins.rst
docs/ebooklib.rst
docs/index.rst
docs/_themes/sphinx_rtd_theme/__init__.py
ebooklib/__init__.py
ebooklib/epub.py
ebooklib/utils.py
ebooklib/plugins/__init__.py
ebooklib/plugins/base.py
ebooklib/plugins/booktype.py
ebooklib/plugins/sourcecode.py
ebooklib/plugins/standard.py
ebooklib/plugins/tidyhtml.py
samples/README.md
samples/01_basic_create/README.md
samples/01_basic_create/create.py
samples/02_cover_create/README.md
samples/02_cover_create/cover.jpg
samples/02_cover_create/create.py
samples/03_advanced_create/README.md
samples/03_advanced_create/create.py
samples/04_markdown_parse/README.md
samples/04_markdown_parse/epub2markdown.py
samples/04_markdown_parse/test/about.md
samples/04_markdown_parse/test/intro.md
samples/04_markdown_parse/test/nav.md
samples/05_plugins_create/README.md
samples/05_plugins_create/create.py
samples/06_parse/README.md
samples/06_parse/parse.py
samples/06_wordpress_create/README.md
samples/06_wordpress_create/import_wordpress.py
samples/07_rtl/README.md
samples/07_rtl/create.py
samples/08_SMIL/README.md