Metadata-Version: 1.1
Name: EbookLib
Version: 0.17
Summary: Ebook library which can handle EPUB2/EPUB3 and Kindle format
Home-page: https://github.com/aerkalov/ebooklib
Author: Aleksandar Erkalovic
Author-email: aerkalov@gmail.com
License: GNU Affero General Public License
Keywords: ebook,epub,kindle
Platform: UNKNOWN
Classifier: Development Status :: 4 - Beta
Classifier: Intended Audience :: Developers
Classifier: Operating System :: OS Independent
Classifier: Programming Language :: Python :: 2.7
Classifier: Programming Language :: Python :: 3.3
Classifier: Programming Language :: Python :: 3.4
Classifier: Programming Language :: Python :: 3.5
Classifier: Programming Language :: Python :: 3.6
Classifier: Topic :: Software Development :: Libraries :: Python Modules
